rsfc/__init__.py
rsfc/harvesters/__init__.py
rsfc/harvesters/cff_harvester.py
rsfc/harvesters/codemeta_harvester.py
rsfc/harvesters/github_harvester.py
rsfc/harvesters/somef_harvester.py
rsfc/main.py
rsfc/model/__init__.py
rsfc/model/assessedSoftware.py
rsfc/model/assessment.py
rsfc/model/check.py
rsfc/model/indicator.py
rsfc/rsfc_core.py
rsfc/rsfc_tests/__init__.py
rsfc/rsfc_tests/rsfc_tests.py
rsfc/templates/assessment_schema.json.j2
rsfc/templates/assessment_schema_ftr.json.j2
rsfc/utils/__init__.py
rsfc/utils/constants.py
rsfc/utils/rsfc_helpers.py
rsfc-0.0.6.dist-info/METADATA
rsfc-0.0.6.dist-info/WHEEL
rsfc-0.0.6.dist-info/entry_points.txt
rsfc-0.0.6.dist-info/licenses/LICENSE
rsfc-0.0.6.dist-info/RECORD
